{
    "keep": {
        "days": true,
        "amount": 14
    },
    "auditLog": "C:\\Users\\ADMIN\\Desktop\\TheBrothersBarberShop\\backend\\logs\\.96951cc03eaf400a6d546721177578c8f2ba48d8-audit.json",
    "files": [
        {
            "date": 1757510457614,
            "name": "C:\\Users\\ADMIN\\Desktop\\TheBrothersBarberShop\\backend\\logs\\2025-09-10-error.log",
            "hash": "09c1fb08b881613c7beda8e43048409870bc432d3591779408ae16970841002d"
        },
        {
            "date": 1757579085379,
            "name": "C:\\Users\\ADMIN\\Desktop\\TheBrothersBarberShop\\backend\\logs\\2025-09-11-error.log",
            "hash": "95d41f47d51b726f5bac6bbb1efbaacc07f22f23c74a6c9b8ba27380e4e676a8"
        },
        {
            "date": 1757694141221,
            "name": "C:\\Users\\ADMIN\\Desktop\\TheBrothersBarberShop\\backend\\logs\\2025-09-12-error.log",
            "hash": "d4b0967b7be5a5297600399e99fcfbc7899e945426b35c81cf8bc1b17de03c1c"
        },
        {
            "date": 1757742937833,
            "name": "C:\\Users\\ADMIN\\Desktop\\TheBrothersBarberShop\\backend\\logs\\2025-09-13-error.log",
            "hash": "f2abf162995d4389068f90aac1c3893b803bfbc320f5dc4835b50e33e8e29ab8"
        },
        {
            "date": 1757826625608,
            "name": "C:\\Users\\ADMIN\\Desktop\\TheBrothersBarberShop\\backend\\logs\\2025-09-14-error.log",
            "hash": "da894ab317c8cce13eb364193ffda9b74870bea6002e0e5e0c01b23cf7580565"
        },
        {
            "date": 1757938973228,
            "name": "C:\\Users\\ADMIN\\Desktop\\TheBrothersBarberShop\\backend\\logs\\2025-09-15-error.log",
            "hash": "b3155f9a0b8573c0a0088948080f588655816e0ccb3e80e9bcd9fbf540691d09"
        },
        {
            "date": 1758025883569,
            "name": "C:\\Users\\ADMIN\\Desktop\\TheBrothersBarberShop\\backend\\logs\\2025-09-16-error.log",
            "hash": "bc35758bb3df1a9db8571c2af0a479ee85b16fd6af242f1a21f7dcc1785e1a28"
        }
    ],
    "hashType": "sha256"
}